logs/__init__.py
logs/custom_logs.py
snapdedup/__init__.py
snapdedup/snap_deduplication.py
snapdedup/snap_differentiator.py
snapdedup-0.0.2.dist-info/licenses/LICENSE
tests/__init__.py
tests/test_snap_differentiator.py
snapdedup-0.0.2.dist-info/METADATA
snapdedup-0.0.2.dist-info/WHEEL
snapdedup-0.0.2.dist-info/top_level.txt
snapdedup-0.0.2.dist-info/RECORD
