Metadata-Version: 2.4
Name: snapdedup
Version: 0.0.2
Summary: Python Library to process and compare images.
Home-page: https://github.com/Sarthak-Gholap/snapdedup
Author: Sarthak, Harshit
Author-email: sarthak6jan16@gmail.com
License: MIT
Keywords: image,deduplication,image processing,duplicate images,image comparison,image similarity,image hash,image matching,duplicate image finder,image uniqueness,image optimization,image deduplication tool,image dedupe,image analysis,fast deduplication,image library
Classifier: License :: OSI Approved :: MIT License
Classifier: Programming Language :: Python
Classifier: Programming Language :: Python :: 3
Classifier: Topic :: Software Development :: Libraries
Requires-Python: >=3.11
License-File: LICENSE
Requires-Dist: opencv-python
Requires-Dist: opencv-python-headless
Requires-Dist: scikit-image
Requires-Dist: setuptools
Requires-Dist: pytest
Requires-Dist: pillow
Dynamic: author
Dynamic: author-email
Dynamic: classifier
Dynamic: description
Dynamic: description-content-type
Dynamic: home-page
Dynamic: keywords
Dynamic: license
Dynamic: license-file
Dynamic: requires-dist
Dynamic: requires-python
Dynamic: summary
